[{"word":"Strong","frequency":75,"sentiment":"Positive"},{"word":"Endorsement","frequency":51,"sentiment":"Positive"},{"word":"Reform","frequency":45,"sentiment":"Positive"},{"word":"Win","frequency":44,"sentiment":"Positive"},{"word":"Fantastic","frequency":40,"sentiment":"Positive"},{"word":"Fair","frequency":33,"sentiment":"Positive"},{"word":"Incredible","frequency":30,"sentiment":"Positive"},{"word":"Congratulations","frequency":29,"sentiment":"Positive"},{"word":"Tough","frequency":28,"sentiment":"Positive"},{"word":"Loves","frequency":26,"sentiment":"Positive"},{"word":"Protect","frequency":22,"sentiment":"Positive"},{"word":"Happy","frequency":20,"sentiment":"Positive"},{"word":"Proud","frequency":20,"sentiment":"Positive"},{"word":"Love","frequency":18,"sentiment":"Positive"},{"word":"Success","frequency":18,"sentiment":"Positive"},{"word":"Beautiful","frequency":17,"sentiment":"Positive"},{"word":"Protection","frequency":17,"sentiment":"Positive"},{"word":"Wonderful","frequency":17,"sentiment":"Positive"},{"word":"Fast","frequency":16,"sentiment":"Positive"},{"word":"Free","frequency":16,"sentiment":"Positive"}]
