[{"word":"Wow","frequency":34,"sentiment":"Positive"},{"word":"Enjoy","frequency":30,"sentiment":"Positive"},{"word":"Win","frequency":19,"sentiment":"Positive"},{"word":"Won","frequency":16,"sentiment":"Positive"},{"word":"Victory","frequency":12,"sentiment":"Positive"},{"word":"Love","frequency":10,"sentiment":"Positive"},{"word":"Nice","frequency":10,"sentiment":"Positive"},{"word":"Positive","frequency":10,"sentiment":"Positive"},{"word":"Success","frequency":9,"sentiment":"Positive"},{"word":"Wonderful","frequency":9,"sentiment":"Positive"},{"word":"Correct","frequency":8,"sentiment":"Positive"},{"word":"Winning","frequency":8,"sentiment":"Positive"},{"word":"Fair","frequency":7,"sentiment":"Positive"},{"word":"Happy","frequency":7,"sentiment":"Positive"},{"word":"Intelligence","frequency":7,"sentiment":"Positive"},{"word":"Powerful","frequency":7,"sentiment":"Positive"},{"word":"Respect","frequency":7,"sentiment":"Positive"},{"word":"Congratulations","frequency":6,"sentiment":"Positive"},{"word":"Fantastic","frequency":6,"sentiment":"Positive"},{"word":"Lead","frequency":6,"sentiment":"Positive"}]
